{
    "Name": "Square2d",
    "ShortName": "Square2d",
    "Models":
    {
        "equations":"levelset"
    },
    "Parameters":
    {
        "x0": "-0.3",
        "y0": "-0.3",
        "r0": "0.08"
    },

    "Materials":
    {
        "levelset":
        {
            "markers":"Omega",
            "levelset_phi_beta":"{0.5*y, -0.5*x}:x:y" // advection velocity: rotation
            //"levelset_phi_beta":"{0.1*(1-y*y/(0.5*0.5)),0}:y" // advection velocity: poiseuille
        }
    },

    "InitialConditions":
    {
        "levelset":
        {
            "Expression":
            {
                "drop1":
                {
                    "expr":"sqrt( (x-x0)*(x-x0) + (y-y0)*(y-y0) ) - r0 :x:x0:y:y0:r0"
                }
            },
            "Shapes":
            {
                "drop2":
                {
                    "shape": "sphere",
                    "xc": "-0.1",
                    "yc": "-0.05",
                    "radius": "0.16"
                },
                "drop3":
                {
                    "shape": "sphere",
                    "xc": "-0.25",
                    "yc": "0.3",
                    "radius": "0.05"
                }
            }
        }
    },
    "BoundaryConditions":
    {
        "levelset":
        {
//            "inflow":
//            {
//                "Left":
//                {
//                    "expr":"0"
//                }
//            }
        }
    },
    "PostProcess":
    {
        "Exports":
        {
            "fields": ["phi", "normal", "curvature"]
        },
        "Measures":
        {
            "quantities": ["volume"]
        }
    }
}
