{
    "Name":"Box",
    "Models": { "equations":"hdg" },
    "Materials":
    {
        "omega1":
        {
	        "name":"bottom",
            "k":"1"
        },
	    "omega2":
	    {
	        "name":"top",
	        "k":"1"
	    },
	    "plate":
	    {
	        "name":"insulation",
	        "k":"1"
	    }
    },
    "BoundaryConditions":
    {
        "temperature":
        {
	        "Neumann":
	        {
                "gamma1":
                {
                    "expr":"1"
                }
            },
            "Robin":
            {
                "gamma2":
                {
                    "expr1":"0.1",
                    "expr2":"0"
                }
	        }
        }
    },
    "PostProcess":
    {
        "Measures":
        {
            "Statistics":
            {
                "sensor":
                {
                    "type":"mean",
                    "field":"temperature",
                    "markers":"gamma1"
                }
            }
        }
    }
}
